lab1/iVerilog/JohnsonCounterTop.v
	`include "JohnsonCounter.v"
	module testBench;
	 // connect the two modules
	 wire clk, rst;
	 wire [3:0] q;
	 
	// declare an instance of the AND module
	 johnsonCounter counter (.out(q), .clk(clk), .rst(rst));

	// declare an instance of the testIt module
	 Tester curTest (.qOut(q), .clk(clk), .rst(rst));
	 
	endmodule 

	module Tester (qOut, clk, rst);

	 input [3:0] qOut;
	 output clk,rst;
	 reg D, clk, rst;
	 reg [21:0] tBase;
	 parameter period = 5;
	 parameter stimDelay = 20;
	 
	 always
		#period clk = ~clk;

		initial 
		begin
		clk = 0;
		rst = 0;
		end
    // always @(posedge clk) tBase <= tBase + 1'b1;
	   initial
		begin
	// these two files support gtkwave and are required
	 $dumpfile("johnsonCounter.vcd");
	 $dumpvars;
	 end
	 
	 always @(posedge clk) 
	 begin
	 $monitor($time, "qOut = %b", qOut);
	 
	 repeat(2)
	 begin 
	 #stimDelay rst = 0;
	 #stimDelay rst = 1;
	 #stimDelay rst = 1;
	 #stimDelay rst = 1;
	 end
	 
	 #(20*period); // needed to see END of simulation
	 $stop;
	 $finish; // finish simulation
	 end
	endmodule

lab1/iVerilog/JohnsonCounter.v
module DFlipFlop(q, qBar, D, clk, rst);
	input D, clk, rst;
	output q, qBar;
	reg q;
	not n1 (qBar, q);
	always@ (negedge rst or posedge clk)
		begin
		if(!rst)
		q = 0;
		else
	q = D;
	end
endmodule

module johnsonCounter(out,clk, rst);
	input clk, rst;
	output[3:0] out;
	reg [3:0] out;
	
	parameter state0 = 4'b1111;
	parameter state1 = 4'b0111;
	parameter state2 = 4'b0011;
	parameter state3 = 4'b0001;
	parameter state4 = 4'b0000;
	parameter state5 = 4'b1000;
	parameter state6 = 4'b1100;
	parameter state7 = 4'b1110;
	
	always @(posedge clk) 
	begin
	if (~rst)
	begin
	out = state0;
	end
	
	else 
	begin 
	case(out)
	
	state0: 
	out = 4'b0111;
	state1: 
	out = 4'b0011;
	state2: 
	out = 4'b0001;
	state3: 
	out = 4'b0000;
	state4: 
	out = 4'b1000;
	state5: 
	out = 4'b1100;
	state6: 
	out = 4'b1110;
	state7: 
	out = 4'b1111;
	endcase
	end

	end
	
	endmodule

lab1/iVerilog/johnsonCounter.vcd
$date
	Tue Jan 10 15:29:39 2017
$end
$version
	Icarus Verilog
$end
$timescale
	1s
$end
$scope module DFlipFlop $end
$var wire 1 ! D $end
$var wire 1 " clk $end
$var wire 1 # qBar $end
$var wire 1 $ rst $end
$var reg 1 % q $end
$upscope $end
$scope module testBench $end
$var wire 1 & rst $end
$var wire 4 ' q [3:0] $end
$var wire 1 ( clk $end
$scope module counter $end
$var wire 1 & rst $end
$var wire 1 ( clk $end
$var reg 4 ) out [3:0] $end
$upscope $end
$scope module curTest $end
$var wire 4 * qOut [3:0] $end
$var reg 1 ( clk $end
$var reg 1 & rst $end
$upscope $end
$upscope $end
$enddefinitions $end
#0
$dumpvars
bx *
bx )
0(
bx '
0&
x%
z$
x#
z"
z!
$end
#5
b1111 '
b1111 )
b1111 *
1(
#10
0(
#15
1(
#20
0(
#25
1(
#30
0(
#35
1(
#40
0(
#45
b111 '
b111 )
b111 *
1(
1&
#50
0(
#55
b11 '
b11 )
b11 *
1(
#60
0(
#65
b1 '
b1 )
b1 *
1(
#70
0(
#75
b0 '
b0 )
b0 *
1(
#80
0(
#85
b1000 '
b1000 )
b1000 *
1(
#90
0(
#95
b1100 '
b1100 )
b1100 *
1(
#100
0(
#105
b1111 '
b1111 )
b1111 *
1(
0&
#110
0(
#115
1(
#120
0(
#125
b111 '
b111 )
b111 *
1(
1&
#130
0(
#135
b11 '
b11 )
b11 *
1(
#140
0(
#145
b1 '
b1 )
b1 *
1(
#150
0(
#155
b0 '
b0 )
b0 *
1(
#160
0(
#165
b1000 '
b1000 )
b1000 *
1(
#170
0(
#175
b1100 '
b1100 )
b1100 *
1(
#180
0(
#185
b1110 '
b1110 )
b1110 *
1(
#190
0(
#195
b1111 '
b1111 )
b1111 *
1(
#200
0(
#205
b111 '
b111 )
b111 *
1(
#210
0(
#215
b11 '
b11 )
b11 *
1(
#220
0(
#225
b1 '
b1 )
b1 *
1(
#230
0(
#235
b0 '
b0 )
b0 *
1(
#240
0(
#245
b1000 '
b1000 )
b1000 *
1(
#250
0(
#255
b1100 '
b1100 )
b1100 *
1(
