lab1/iVerilog/syncDown.v
module DFlipFlop(q, qBar, D, clk, rst);
	input D, clk, rst;
	output q, qBar;
	reg q;
	not n1 (qBar, q);
	always@ (negedge rst or posedge clk)
		begin
		if(!rst)
		q = 0;
		else
	q = D;
	end
endmodule

module syncDown(qOut, clk, rst);

	input clk, rst;
	output [3:0] qOut;
	wire d0, d1, d2, d3;
	wire [3:0] Qbar;
	
	assign d0 = Qbar[0];
	assign d1 = ~(qOut[1] ^ qOut[0]);
	assign d2 = ~(qOut[2] ^ (qOut[1]|qOut[0]));
	assign d3 = ~(qOut[3] ^ (qOut[2]|qOut[1]|qOut[0]));

	DFlipFlop ff0 (.q(qOut[0]), .qBar(Qbar[0]), .D(d0), .clk(clk), .rst(rst));
	DFlipFlop ff1 (.q(qOut[1]), .qBar(Qbar[1]), .D(d1), .clk(clk), .rst(rst));
	DFlipFlop ff2 (.q(qOut[2]), .qBar(Qbar[2]), .D(d2), .clk(clk), .rst(rst));
	DFlipFlop ff3 (.q(qOut[3]), .qBar(Qbar[3]), .D(d3), .clk(clk), .rst(rst));

endmodule

lab1/iVerilog/syncDownTop.v
	`include "syncDown.v"
	module testBench;
	 // connect the two modules
	 wire clk, rst;
	 wire [3:0] q;
	 
	// declare an instance of the AND module
	 syncDown counter (.qOut(q), .clk(clk), .rst(rst));

	// declare an instance of the testIt module
	 Tester aTester (.qOut(q), .clk(clk), .rst(rst));
	 
	endmodule 

	module Tester (qOut, clk, rst);

	 input [3:0] qOut;
	 output clk,rst;
	 reg D, clk, rst;
	 parameter period = 5;
	 parameter stimDelay = 20;
	 
	 always
		#period clk = ~clk;

		initial 
		begin
		clk = 0;
		rst = 0;
		end
		
	   initial
		begin
	// these two files support gtkwave and are required
	 $dumpfile("syncDown.vcd");
	 $dumpvars;
	 end
	 
	 always @(posedge clk) 
	 begin
	 $monitor($time, "qOut = %b", qOut);
	 
	 repeat(2)
	 begin 
	 #stimDelay rst = 0;
	 #stimDelay rst = 1;
	 #stimDelay rst = 1;
	 #stimDelay rst = 1;
	 end
	 
	 #(20*period); // needed to see END of simulation
	 $stop;
	 $finish; // finish simulation
	 end
	endmodule

lab1/iVerilog/syncDown.vcd
$date
	Tue Jan 10 15:34:29 2017
$end
$version
	Icarus Verilog
$end
$timescale
	1s
$end
$scope module testBench $end
$var wire 1 ! rst $end
$var wire 4 " q [3:0] $end
$var wire 1 # clk $end
$scope module aTester $end
$var wire 4 $ qOut [3:0] $end
$var reg 1 # clk $end
$var reg 1 ! rst $end
$upscope $end
$scope module counter $end
$var wire 1 # clk $end
$var wire 1 % d1 $end
$var wire 1 & d2 $end
$var wire 1 ' d3 $end
$var wire 1 ! rst $end
$var wire 4 ( qOut [3:0] $end
$var wire 1 ) d0 $end
$var wire 4 * Qbar [3:0] $end
$scope module ff0 $end
$var wire 1 ) D $end
$var wire 1 # clk $end
$var wire 1 + qBar $end
$var wire 1 ! rst $end
$var reg 1 , q $end
$upscope $end
$scope module ff1 $end
$var wire 1 % D $end
$var wire 1 # clk $end
$var wire 1 - qBar $end
$var wire 1 ! rst $end
$var reg 1 . q $end
$upscope $end
$scope module ff2 $end
$var wire 1 & D $end
$var wire 1 # clk $end
$var wire 1 / qBar $end
$var wire 1 ! rst $end
$var reg 1 0 q $end
$upscope $end
$scope module ff3 $end
$var wire 1 ' D $end
$var wire 1 # clk $end
$var wire 1 1 qBar $end
$var wire 1 ! rst $end
$var reg 1 2 q $end
$upscope $end
$upscope $end
$upscope $end
$enddefinitions $end
#0
$dumpvars
02
11
00
1/
0.
1-
0,
1+
b1111 *
1)
b0 (
1'
1&
1%
b0 $
0#
b0 "
0!
$end
#5
1#
#10
0#
#15
1#
#20
0#
#25
1#
#30
0#
#35
1#
#40
0#
#45
0)
01
0/
0-
b0 *
0+
12
10
1.
b1111 "
b1111 $
b1111 (
1,
1#
1!
#50
0#
#55
0%
1)
b1 *
1+
b1110 "
b1110 $
b1110 (
0,
1#
#60
0#
#65
0)
1-
b10 *
0+
0.
b1101 "
b1101 $
b1101 (
1,
1#
#70
0#
#75
0&
1%
1)
b11 *
1+
b1100 "
b1100 $
b1100 (
0,
1#
#80
0#
#85
0)
1/
0-
b100 *
0+
00
1.
b1011 "
b1011 $
b1011 (
1,
1#
#90
0#
#95
0%
1)
b101 *
1+
b1010 "
b1010 $
b1010 (
0,
1#
#100
0#
#105
1&
1'
1%
11
b1111 *
1-
02
b0 "
b0 $
b0 (
0.
1#
0!
#110
0#
#115
1#
#120
0#
#125
0)
01
0/
0-
b0 *
0+
12
10
1.
b1111 "
b1111 $
b1111 (
1,
1#
1!
#130
0#
#135
0%
1)
b1 *
1+
b1110 "
b1110 $
b1110 (
0,
1#
#140
0#
#145
0)
1-
b10 *
0+
0.
b1101 "
b1101 $
b1101 (
1,
1#
#150
0#
#155
0&
1%
1)
b11 *
1+
b1100 "
b1100 $
b1100 (
0,
1#
#160
0#
#165
0)
1/
0-
b100 *
0+
00
1.
b1011 "
b1011 $
b1011 (
1,
1#
#170
0#
#175
0%
1)
b101 *
1+
b1010 "
b1010 $
b1010 (
0,
1#
#180
0#
#185
0)
1-
b110 *
0+
0.
b1001 "
b1001 $
b1001 (
1,
1#
#190
0#
#195
0'
1&
1%
1)
b111 *
1+
b1000 "
b1000 $
b1000 (
0,
1#
#200
0#
#205
0)
11
0/
0-
b1000 *
0+
02
10
1.
b111 "
b111 $
b111 (
1,
1#
#210
0#
#215
0%
1)
b1001 *
1+
b110 "
b110 $
b110 (
0,
1#
#220
0#
#225
0)
1-
b1010 *
0+
0.
b101 "
b101 $
b101 (
1,
1#
#230
0#
#235
0&
1%
1)
b1011 *
1+
b100 "
b100 $
b100 (
0,
1#
#240
0#
#245
0)
1/
0-
b1100 *
0+
00
1.
b11 "
b11 $
b11 (
1,
1#
#250
0#
#255
0%
1)
b1101 *
1+
b10 "
b10 $
b10 (
0,
1#
